djoffers/__init__.py
djoffers/models.py
djoffers/settings.py
djoffers-0.1.4.dist-info/METADATA
djoffers-0.1.4.dist-info/RECORD
djoffers-0.1.4.dist-info/WHEEL
djoffers-0.1.4.dist-info/top_level.txt
